<?xml version="1.0" encoding="utf-8" ?>
<dwsync>
<file name="icon-16-media.png" server="K:/wampserver/wamp/www/system_red/" local="129467576282835270" remote="129467576280000000" />
<file name="icon-16-messages.png" server="K:/wampserver/wamp/www/system_red/" local="129467576277772692" remote="129467576270000000" />
<file name="icon-16-user.png" server="K:/wampserver/wamp/www/system_red/" local="129467576258852352" remote="129467576250000000" />
<file name="icon-16-logout.png" server="K:/wampserver/wamp/www/system_red/" local="129467576286932839" remote="129467576280000000" />
<file name="icon-16-config.png" server="K:/wampserver/wamp/www/system_red/" local="129467576304145604" remote="129467576300000000" />
<file name="icon-16-archive.png" server="K:/wampserver/wamp/www/system_red/" local="129467576313895753" remote="129467576310000000" />
<file name="icon-16-article.png" server="K:/wampserver/wamp/www/system_red/" local="129467576311833222" remote="129467576310000000" />
<file name="icon-16-category.png" server="K:/wampserver/wamp/www/system_red/" local="129467576309983193" remote="129467576300000000" />
<file name="icon-16-checkin.png" server="K:/wampserver/wamp/www/system_red/" local="129467576308083164" remote="129467576300000000" />
<file name="icon-16-component.png" server="K:/wampserver/wamp/www/system_red/" local="129467576306083133" remote="129467576300000000" />
<file name="icon-16-content.png" server="K:/wampserver/wamp/www/system_red/" local="129467576302195574" remote="129467576300000000" />
<file name="icon-16-cpanel.png" server="K:/wampserver/wamp/www/system_red/" local="129467576300458047" remote="129467576300000000" />
<file name="icon-16-default.png" server="K:/wampserver/wamp/www/system_red/" local="129467576298395515" remote="129467576290000000" />
<file name="icon-16-frontpage.png" server="K:/wampserver/wamp/www/system_red/" local="129467576296795491" remote="129467576290000000" />
<file name="icon-16-help.png" server="K:/wampserver/wamp/www/system_red/" local="129467576294595457" remote="129467576290000000" />
<file name="icon-16-info.png" server="K:/wampserver/wamp/www/system_red/" local="129467576293020433" remote="129467576290000000" />
<file name="icon-16-install.png" server="K:/wampserver/wamp/www/system_red/" local="129467576290820399" remote="129467576290000000" />
<file name="icon-16-language.png" server="K:/wampserver/wamp/www/system_red/" local="129467576289057872" remote="129467576280000000" />
<file name="icon-16-massmail.png" server="K:/wampserver/wamp/www/system_red/" local="129467576285345315" remote="129467576280000000" />
<file name="icon-16-menu.png" server="K:/wampserver/wamp/www/system_red/" local="129467576281535250" remote="129467576280000000" />
<file name="icon-16-menumgr.png" server="K:/wampserver/wamp/www/system_red/" local="129467576279022711" remote="129467576270000000" />
<file name="icon-16-module.png" server="K:/wampserver/wamp/www/system_red/" local="129467576275285154" remote="129467576270000000" />
<file name="icon-16-plugin.png" server="K:/wampserver/wamp/www/system_red/" local="129467576273810131" remote="129467576270000000" />
<file name="icon-16-section.png" server="K:/wampserver/wamp/www/system_red/" local="129467576270147575" remote="129467576270000000" />
<file name="icon-16-static.png" server="K:/wampserver/wamp/www/system_red/" local="129467576267497534" remote="129467576260000000" />
<file name="icon-16-stats.png" server="K:/wampserver/wamp/www/system_red/" local="129467576266510019" remote="129467576260000000" />
<file name="icon-16-themes.png" server="K:/wampserver/wamp/www/system_red/" local="129467576262612452" remote="129467576260000000" />
<file name="icon-16-trash.png" server="K:/wampserver/wamp/www/system_red/" local="129467576263674969" remote="129467576260000000" />
<file name="icon-16-media.png" server="C:/wamp/www/system_red/" local="129467576300000000" remote="129467576300000000" />
<file name="icon-16-messages.png" server="C:/wamp/www/system_red/" local="129467576280000000" remote="129467576280000000" />
<file name="icon-16-user.png" server="C:/wamp/www/system_red/" local="129467576260000000" remote="129467576260000000" />
<file name="icon-16-logout.png" server="C:/wamp/www/system_red/" local="129467576300000000" remote="129467576300000000" />
<file name="icon-16-config.png" server="C:/wamp/www/system_red/" local="129467576320000000" remote="129467576320000000" />
<file name="icon-16-media.png" server="C:/wamp/www/red_funcional/" local="129467576300000000" remote="129467576300000000" />
<file name="icon-16-messages.png" server="C:/wamp/www/red_funcional/" local="129467576280000000" remote="129467576280000000" />
<file name="icon-16-user.png" server="C:/wamp/www/red_funcional/" local="129467576260000000" remote="129467576260000000" />
<file name="icon-16-logout.png" server="C:/wamp/www/red_funcional/" local="129467576300000000" remote="129467576300000000" />
<file name="icon-16-config.png" server="C:/wamp/www/red_funcional/" local="129467576320000000" remote="129467576320000000" />
<file name="icon-16-archive.png" server="C:/wamp/www/red_funcional/" local="129467576320000000" remote="129467576320000000" />
<file name="icon-16-article.png" server="C:/wamp/www/red_funcional/" local="129467576320000000" remote="129467576320000000" />
<file name="icon-16-category.png" server="C:/wamp/www/red_funcional/" local="129467576320000000" remote="129467576320000000" />
<file name="icon-16-checkin.png" server="C:/wamp/www/red_funcional/" local="129467576320000000" remote="129467576320000000" />
<file name="icon-16-component.png" server="C:/wamp/www/red_funcional/" local="129467576320000000" remote="129467576320000000" />
<file name="icon-16-content.png" server="C:/wamp/www/red_funcional/" local="129467576320000000" remote="129467576320000000" />
<file name="icon-16-cpanel.png" server="C:/wamp/www/red_funcional/" local="129467576320000000" remote="129467576320000000" />
<file name="icon-16-default.png" server="C:/wamp/www/red_funcional/" local="129467576300000000" remote="129467576300000000" />
<file name="icon-16-frontpage.png" server="C:/wamp/www/red_funcional/" local="129467576300000000" remote="129467576300000000" />
<file name="icon-16-help.png" server="C:/wamp/www/red_funcional/" local="129467576300000000" remote="129467576300000000" />
<file name="icon-16-info.png" server="C:/wamp/www/red_funcional/" local="129467576300000000" remote="129467576300000000" />
<file name="icon-16-install.png" server="C:/wamp/www/red_funcional/" local="129467576300000000" remote="129467576300000000" />
<file name="icon-16-language.png" server="C:/wamp/www/red_funcional/" local="129467576300000000" remote="129467576300000000" />
<file name="icon-16-massmail.png" server="C:/wamp/www/red_funcional/" local="129467576300000000" remote="129467576300000000" />
<file name="icon-16-menu.png" server="C:/wamp/www/red_funcional/" local="129467576300000000" remote="129467576300000000" />
<file name="icon-16-menumgr.png" server="C:/wamp/www/red_funcional/" local="129467576280000000" remote="129467576280000000" />
<file name="icon-16-module.png" server="C:/wamp/www/red_funcional/" local="129467576280000000" remote="129467576280000000" />
<file name="icon-16-plugin.png" server="C:/wamp/www/red_funcional/" local="129467576280000000" remote="129467576280000000" />
<file name="icon-16-section.png" server="C:/wamp/www/red_funcional/" local="129467576280000000" remote="129467576280000000" />
<file name="icon-16-static.png" server="C:/wamp/www/red_funcional/" local="129467576280000000" remote="129467576280000000" />
<file name="icon-16-stats.png" server="C:/wamp/www/red_funcional/" local="129467576280000000" remote="129467576280000000" />
<file name="icon-16-themes.png" server="C:/wamp/www/red_funcional/" local="129467576280000000" remote="129467576280000000" />
<file name="icon-16-trash.png" server="C:/wamp/www/red_funcional/" local="129467576280000000" remote="129467576280000000" />
<file name="icon-16-cpanel.png" server="C:/wamp/www/controlautomotriz/" local="129467576320000000" remote="129467576320000000" />
<file name="icon-16-user.png" server="C:/wamp/www/controlautomotriz/" local="129467576260000000" remote="129467576260000000" />
<file name="icon-16-media.png" server="C:/wamp/www/controlautomotriz/" local="129467576300000000" remote="129467576300000000" />
<file name="icon-16-messages.png" server="C:/wamp/www/controlautomotriz/" local="129467576280000000" remote="129467576280000000" />
<file name="icon-16-logout.png" server="C:/wamp/www/controlautomotriz/" local="129467576300000000" remote="129467576300000000" />
<file name="icon-16-config.png" server="C:/wamp/www/controlautomotriz/" local="129467576320000000" remote="129467576320000000" />
<file name="icon-16-cotizacion.png" server="C:/wamp/www/controlautomotriz/" local="129481830654908947" remote="129481830650000000" />
<file name="icon-16-auto.png" server="C:/wamp/www/controlautomotriz/" local="129481759537142958" remote="129481759530000000" />
<file name="icon-16-cliente.png" server="C:/wamp/www/controlautomotriz/" local="129481770938025057" remote="129481770930000000" />
<file name="icon-16-autoventa.png" server="C:/wamp/www/controlautomotriz/" local="129482685250477469" remote="129482685250000000" />
<file name="icon-16-imprimirhistorial.png" server="C:/wamp/www/controlautomotriz/" local="129482705645195195" remote="129482705640000000" />
<file name="icon-16-adeudo.png" server="C:/wamp/www/controlautomotriz/" local="129482674319817242" remote="129482674310000000" />
<file name="icon-16-pagos.png" server="C:/wamp/www/controlautomotriz/" local="129482639656439558" remote="129482639650000000" />
<file name="icon-16-vencimientos.png" server="C:/wamp/www/controlautomotriz/" local="129482677337595037" remote="129482677330000000" />
<file name="icon-16-abono.png" server="C:/wamp/www/controlautomotriz/" local="129482621693200521" remote="129482621690000000" />
<file name="icon-16-resumen.png" server="C:/wamp/www/controlautomotriz/" local="129482554407364942" remote="129482554400000000" />
<file name="icon-16-deslinde.png" server="C:/wamp/www/controlautomotriz/" local="129482555633019032" remote="129482555630000000" />
<file name="icon-16-pagares.png" server="C:/wamp/www/controlautomotriz/" local="129482551365397692" remote="129482551360000000" />
<file name="icon-16-contrato.png" server="C:/wamp/www/controlautomotriz/" local="129482549105725231" remote="129482549100000000" />
<file name="icon-16-archive.png" server="C:/wamp/www/controlautomotriz/" local="129467576320000000" remote="129467576320000000" />
<file name="icon-16-article.png" server="C:/wamp/www/controlautomotriz/" local="129467576320000000" remote="129467576320000000" />
<file name="icon-16-category.png" server="C:/wamp/www/controlautomotriz/" local="129467576320000000" remote="129467576320000000" />
<file name="icon-16-checkin.png" server="C:/wamp/www/controlautomotriz/" local="129467576320000000" remote="129467576320000000" />
<file name="icon-16-component.png" server="C:/wamp/www/controlautomotriz/" local="129467576320000000" remote="129467576320000000" />
<file name="icon-16-content.png" server="C:/wamp/www/controlautomotriz/" local="129467576320000000" remote="129467576320000000" />
<file name="icon-16-default.png" server="C:/wamp/www/controlautomotriz/" local="129467576300000000" remote="129467576300000000" />
<file name="icon-16-frontpage.png" server="C:/wamp/www/controlautomotriz/" local="129467576300000000" remote="129467576300000000" />
<file name="icon-16-help.png" server="C:/wamp/www/controlautomotriz/" local="129467576300000000" remote="129467576300000000" />
<file name="icon-16-info.png" server="C:/wamp/www/controlautomotriz/" local="129467576300000000" remote="129467576300000000" />
<file name="icon-16-install.png" server="C:/wamp/www/controlautomotriz/" local="129467576300000000" remote="129467576300000000" />
<file name="icon-16-language.png" server="C:/wamp/www/controlautomotriz/" local="129467576300000000" remote="129467576300000000" />
<file name="icon-16-massmail.png" server="C:/wamp/www/controlautomotriz/" local="129467576300000000" remote="129467576300000000" />
<file name="icon-16-menu.png" server="C:/wamp/www/controlautomotriz/" local="129467576300000000" remote="129467576300000000" />
<file name="icon-16-menumgr.png" server="C:/wamp/www/controlautomotriz/" local="129467576280000000" remote="129467576280000000" />
<file name="icon-16-module.png" server="C:/wamp/www/controlautomotriz/" local="129467576280000000" remote="129467576280000000" />
<file name="icon-16-plugin.png" server="C:/wamp/www/controlautomotriz/" local="129467576280000000" remote="129467576280000000" />
<file name="icon-16-section.png" server="C:/wamp/www/controlautomotriz/" local="129467576280000000" remote="129467576280000000" />
<file name="icon-16-static.png" server="C:/wamp/www/controlautomotriz/" local="129467576280000000" remote="129467576280000000" />
<file name="icon-16-stats.png" server="C:/wamp/www/controlautomotriz/" local="129467576280000000" remote="129467576280000000" />
<file name="icon-16-themes.png" server="C:/wamp/www/controlautomotriz/" local="129467576280000000" remote="129467576280000000" />
<file name="icon-16-trash.png" server="C:/wamp/www/controlautomotriz/" local="129467576280000000" remote="129467576280000000" />
<file name="icon-16-clienteaval.png" server="C:/wamp/www/controlautomotriz/" local="129594188958928394" remote="129594188950000000" />
<file name="icon-16-costo.png" server="C:/wamp/www/controlautomotriz/" local="129650146994200464" remote="129650146990000000" />
<file name="icon-16-costo.png" server="K:/wampserver/wamp/www/RedAmpliado/" local="129650147000000000" remote="129650147000000000" />
<file name="icon-16-autoventa.png" server="K:/wampserver/wamp/www/RedAmpliado/" local="129482685260000000" remote="129482685260000000" />
<file name="icon-16-imprimirhistorial.png" server="K:/wampserver/wamp/www/RedAmpliado/" local="129482705660000000" remote="129482705660000000" />
<file name="icon-16-adeudo.png" server="K:/wampserver/wamp/www/RedAmpliado/" local="129482674320000000" remote="129482674320000000" />
<file name="icon-16-pagos.png" server="K:/wampserver/wamp/www/RedAmpliado/" local="129482639660000000" remote="129482639660000000" />
<file name="icon-16-vencimientos.png" server="K:/wampserver/wamp/www/RedAmpliado/" local="129482677340000000" remote="129482677340000000" />
<file name="icon-16-abono.png" server="K:/wampserver/wamp/www/RedAmpliado/" local="129482621700000000" remote="129482621700000000" />
<file name="icon-16-resumen.png" server="K:/wampserver/wamp/www/RedAmpliado/" local="129482554420000000" remote="129482554420000000" />
<file name="icon-16-deslinde.png" server="K:/wampserver/wamp/www/RedAmpliado/" local="129482555640000000" remote="129482555640000000" />
<file name="icon-16-pagares.png" server="K:/wampserver/wamp/www/RedAmpliado/" local="129482551380000000" remote="129482551380000000" />
<file name="icon-16-contrato.png" server="K:/wampserver/wamp/www/RedAmpliado/" local="129482549120000000" remote="129482549120000000" />
<file name="icon-16-cotizacion.png" server="K:/wampserver/wamp/www/RedAmpliado/" local="129481830660000000" remote="129481830660000000" />
<file name="icon-16-auto.png" server="K:/wampserver/wamp/www/RedAmpliado/" local="129481759540000000" remote="129481759540000000" />
<file name="icon-16-cliente.png" server="K:/wampserver/wamp/www/RedAmpliado/" local="129481770940000000" remote="129481770940000000" />
<file name="icon-16-clienteaval.png" server="K:/wampserver/wamp/www/RedAmpliado/" local="129594188960000000" remote="129594188960000000" />
<file name="icon-16-cpanel.png" server="K:/wampserver/wamp/www/RedAmpliado/" local="129467576320000000" remote="129467576320000000" />
<file name="icon-16-user.png" server="K:/wampserver/wamp/www/RedAmpliado/" local="129467576260000000" remote="129467576260000000" />
<file name="icon-16-media.png" server="K:/wampserver/wamp/www/RedAmpliado/" local="129467576300000000" remote="129467576300000000" />
<file name="icon-16-messages.png" server="K:/wampserver/wamp/www/RedAmpliado/" local="129467576280000000" remote="129467576280000000" />
<file name="icon-16-logout.png" server="K:/wampserver/wamp/www/RedAmpliado/" local="129467576300000000" remote="129467576300000000" />
<file name="icon-16-config.png" server="K:/wampserver/wamp/www/RedAmpliado/" local="129467576320000000" remote="129467576320000000" />
<file name="icon-16-red-rama.png" server="K:/wampserver/wamp/www/RedAmpliado/" local="129804521463414991" remote="129804521460000000" />
<file name="icon-16-red-modalidadentedep.png" server="K:/wampserver/wamp/www/RedAmpliado/" local="129804528784771973" remote="129804528780000000" />
<file name="icon-16-red-deportes.png" server="K:/wampserver/wamp/www/RedAmpliado/" local="129804530159075654" remote="129804530150000000" />
<file name="icon-16-red-club.png" server="K:/wampserver/wamp/www/RedAmpliado/" local="129804532388728593" remote="129804532380000000" />
<file name="icon-16-red-liga.png" server="K:/wampserver/wamp/www/RedAmpliado/" local="129804537045200115" remote="129804537040000000" />
<file name="icon-16-red-eventonacional.png" server="K:/wampserver/wamp/www/RedAmpliado/" local="129804538455081771" remote="129804538450000000" />
<file name="icon-16-red-municipio.png" server="K:/wampserver/wamp/www/RedAmpliado/" local="129804542429857065" remote="129804542420000000" />
<file name="icon-16-red-asociaciondep.png" server="K:/wampserver/wamp/www/RedAmpliado/" local="129804550508842247" remote="129804550500000000" />
<file name="icon-16-red-pruebas.png" server="K:/wampserver/wamp/www/RedAmpliado/" local="129804561513000400" remote="129804561510000000" />
<file name="icon-16-red-modalidaddeportiva.png" server="K:/wampserver/wamp/www/RedAmpliado/" local="129804607400255001" remote="129804607400000000" />
<file name="icon-16-red-eventointernacional.png" server="K:/wampserver/wamp/www/RedAmpliado/" local="129804609939160218" remote="129804609930000000" />
<file name="icon-16-red-estado.png" server="K:/wampserver/wamp/www/RedAmpliado/" local="129804612114544643" remote="129804612110000000" />
<file name="icon-16-red-categoria.png" server="K:/wampserver/wamp/www/RedAmpliado/" local="129804619324586391" remote="129804619320000000" />
<file name="icon-16-red-vincularasociaciondep.png" server="K:/wampserver/wamp/www/RedAmpliado/" local="129805382789061431" remote="129805382780000000" />
<file name="icon-16-red-imprimirasociaciondep.png" server="K:/wampserver/wamp/www/RedAmpliado/" local="129805412179198763" remote="129805412170000000" />
<file name="icon-16-red-imprimirsirred.png" server="K:/wampserver/wamp/www/RedAmpliado/" local="129805414741313278" remote="129805414740000000" />
<file name="icon-16-red-cedulainscripcion.png" server="K:/wampserver/wamp/www/RedAmpliado/" local="129805416675267999" remote="129805416670000000" />
<file name="icon-16-red-imprimircredencial.png" server="K:/wampserver/wamp/www/RedAmpliado/" local="129805422868458550" remote="129805422860000000" />
<file name="icon-16-red-reporteasociaciondep.png" server="K:/wampserver/wamp/www/RedAmpliado/" local="129805426492178405" remote="129805426490000000" />
<file name="icon-16-red-vincularevaluacionseg.png" server="K:/wampserver/wamp/www/RedAmpliado/" local="129805506838521501" remote="129805506830000000" />
<file name="icon-16-red-imprimirevaluacionseg.png" server="K:/wampserver/wamp/www/RedAmpliado/" local="129805511691236070" remote="129805511690000000" />
<file name="icon-16-red-curriculumevaluacionseg.png" server="K:/wampserver/wamp/www/RedAmpliado/" local="129805515338159610" remote="129805515330000000" />
<file name="icon-16-red-reporteevaluacionseg.png" server="K:/wampserver/wamp/www/RedAmpliado/" local="129806271512064755" remote="129806271510000000" />
<file name="icon-16-red-vinculareventodep.png" server="K:/wampserver/wamp/www/RedAmpliado/" local="129806358607176315" remote="129806358600000000" />
<file name="icon-16-red-validareventodep.png" server="K:/wampserver/wamp/www/RedAmpliado/" local="129806360480332599" remote="129806360480000000" />
<file name="icon-16-red-resultadoeventodep.png" server="K:/wampserver/wamp/www/RedAmpliado/" local="129806363430962943" remote="129806363430000000" />
<file name="icon-16-red-impimireventodep.png" server="K:/wampserver/wamp/www/RedAmpliado/" local="129806373099071477" remote="129806373090000000" />
<file name="icon-16-red-impimircedulaeventodep.png" server="K:/wampserver/wamp/www/RedAmpliado/" local="129806374938187225" remote="129806374930000000" />
<file name="icon-16-red-impimirgaffeteseventodep.png" server="K:/wampserver/wamp/www/RedAmpliado/" local="129808854634515589" remote="129808854630000000" />
<file name="icon-16-red-reporteeventodep.png" server="K:/wampserver/wamp/www/RedAmpliado/" local="129808868511620296" remote="129808868510000000" />
<file name="icon-16-red-imprimirreportecredencial.png" server="K:/wampserver/wamp/www/RedAmpliado/" local="129808871345869390" remote="129808871340000000" />
<file name="icon-16-red-reportes.png" server="K:/wampserver/wamp/www/RedAmpliado/" local="129808875967073831" remote="129808875960000000" />
<file name="icon-16-red-status.png" server="K:/wampserver/wamp/www/RedAmpliado/" local="129808877607640216" remote="129808877600000000" />
<file name="icon-16-costo.png" server="C:/wamp/www/redampliado/" local="129650147000000000" remote="129650147000000000" />
<file name="icon-16-autoventa.png" server="C:/wamp/www/redampliado/" local="129482685260000000" remote="129482685260000000" />
<file name="icon-16-imprimirhistorial.png" server="C:/wamp/www/redampliado/" local="129482705660000000" remote="129482705660000000" />
<file name="icon-16-adeudo.png" server="C:/wamp/www/redampliado/" local="129482674320000000" remote="129482674320000000" />
<file name="icon-16-pagos.png" server="C:/wamp/www/redampliado/" local="129482639660000000" remote="129482639660000000" />
<file name="icon-16-vencimientos.png" server="C:/wamp/www/redampliado/" local="129482677340000000" remote="129482677340000000" />
<file name="icon-16-abono.png" server="C:/wamp/www/redampliado/" local="129482621700000000" remote="129482621700000000" />
<file name="icon-16-resumen.png" server="C:/wamp/www/redampliado/" local="129482554420000000" remote="129482554420000000" />
<file name="icon-16-deslinde.png" server="C:/wamp/www/redampliado/" local="129482555640000000" remote="129482555640000000" />
<file name="icon-16-pagares.png" server="C:/wamp/www/redampliado/" local="129482551380000000" remote="129482551380000000" />
<file name="icon-16-contrato.png" server="C:/wamp/www/redampliado/" local="129482549120000000" remote="129482549120000000" />
<file name="icon-16-cotizacion.png" server="C:/wamp/www/redampliado/" local="129481830660000000" remote="129481830660000000" />
<file name="icon-16-auto.png" server="C:/wamp/www/redampliado/" local="129481759540000000" remote="129481759540000000" />
<file name="icon-16-cliente.png" server="C:/wamp/www/redampliado/" local="129481770940000000" remote="129481770940000000" />
<file name="icon-16-clienteaval.png" server="C:/wamp/www/redampliado/" local="129594188960000000" remote="129594188960000000" />
<file name="icon-16-cpanel.png" server="C:/wamp/www/redampliado/" local="129467576320000000" remote="129467576320000000" />
<file name="icon-16-user.png" server="C:/wamp/www/redampliado/" local="129467576260000000" remote="129467576260000000" />
<file name="icon-16-red-rama.png" server="C:/wamp/www/redampliado/" local="129804521480000000" remote="129804521480000000" />
<file name="icon-16-red-modalidadentedep.png" server="C:/wamp/www/redampliado/" local="129804528800000000" remote="129804528800000000" />
<file name="icon-16-red-deportes.png" server="C:/wamp/www/redampliado/" local="129804530160000000" remote="129804530160000000" />
<file name="icon-16-red-club.png" server="C:/wamp/www/redampliado/" local="129804532400000000" remote="129804532400000000" />
<file name="icon-16-red-liga.png" server="C:/wamp/www/redampliado/" local="129804537060000000" remote="129804537060000000" />
<file name="icon-16-red-eventonacional.png" server="C:/wamp/www/redampliado/" local="129804538460000000" remote="129804538460000000" />
<file name="icon-16-red-municipio.png" server="C:/wamp/www/redampliado/" local="129804542440000000" remote="129804542440000000" />
<file name="icon-16-red-asociaciondep.png" server="C:/wamp/www/redampliado/" local="129804550520000000" remote="129804550520000000" />
<file name="icon-16-red-pruebas.png" server="C:/wamp/www/redampliado/" local="129804561520000000" remote="129804561520000000" />
<file name="icon-16-red-modalidaddeportiva.png" server="C:/wamp/www/redampliado/" local="129804607420000000" remote="129804607420000000" />
<file name="icon-16-red-eventointernacional.png" server="C:/wamp/www/redampliado/" local="129804609940000000" remote="129804609940000000" />
<file name="icon-16-red-estado.png" server="C:/wamp/www/redampliado/" local="129804612120000000" remote="129804612120000000" />
<file name="icon-16-red-categoria.png" server="C:/wamp/www/redampliado/" local="129804619340000000" remote="129804619340000000" />
<file name="icon-16-red-vincularasociaciondep.png" server="C:/wamp/www/redampliado/" local="129805382800000000" remote="129805382800000000" />
<file name="icon-16-red-imprimirasociaciondep.png" server="C:/wamp/www/redampliado/" local="129805412180000000" remote="129805412180000000" />
<file name="icon-16-red-imprimirsirred.png" server="C:/wamp/www/redampliado/" local="129805414760000000" remote="129805414760000000" />
<file name="icon-16-red-cedulainscripcion.png" server="C:/wamp/www/redampliado/" local="129805416680000000" remote="129805416680000000" />
<file name="icon-16-red-imprimircredencial.png" server="C:/wamp/www/redampliado/" local="129805422880000000" remote="129805422880000000" />
<file name="icon-16-red-reporteasociaciondep.png" server="C:/wamp/www/redampliado/" local="129805426500000000" remote="129805426500000000" />
<file name="icon-16-red-vincularevaluacionseg.png" server="C:/wamp/www/redampliado/" local="129805506840000000" remote="129805506840000000" />
<file name="icon-16-red-imprimirevaluacionseg.png" server="C:/wamp/www/redampliado/" local="129805511700000000" remote="129805511700000000" />
<file name="icon-16-red-curriculumevaluacionseg.png" server="C:/wamp/www/redampliado/" local="129805515340000000" remote="129805515340000000" />
<file name="icon-16-red-reporteevaluacionseg.png" server="C:/wamp/www/redampliado/" local="129806271520000000" remote="129806271520000000" />
<file name="icon-16-red-vinculareventodep.png" server="C:/wamp/www/redampliado/" local="129806358620000000" remote="129806358620000000" />
<file name="icon-16-red-validareventodep.png" server="C:/wamp/www/redampliado/" local="129806360500000000" remote="129806360500000000" />
<file name="icon-16-red-resultadoeventodep.png" server="C:/wamp/www/redampliado/" local="129806363440000000" remote="129806363440000000" />
<file name="icon-16-red-impimireventodep.png" server="C:/wamp/www/redampliado/" local="129806373100000000" remote="129806373100000000" />
<file name="icon-16-red-impimircedulaeventodep.png" server="C:/wamp/www/redampliado/" local="129806374940000000" remote="129806374940000000" />
<file name="icon-16-red-impimirgaffeteseventodep.png" server="C:/wamp/www/redampliado/" local="129808854640000000" remote="129808854640000000" />
<file name="icon-16-red-reporteeventodep.png" server="C:/wamp/www/redampliado/" local="129808868520000000" remote="129808868520000000" />
<file name="icon-16-red-imprimirreportecredencial.png" server="C:/wamp/www/redampliado/" local="129808871360000000" remote="129808871360000000" />
<file name="icon-16-red-reportes.png" server="C:/wamp/www/redampliado/" local="129808875980000000" remote="129808875980000000" />
<file name="icon-16-red-status.png" server="C:/wamp/www/redampliado/" local="129808877620000000" remote="129808877620000000" />
<file name="icon-16-media.png" server="C:/wamp/www/redampliado/" local="129467576300000000" remote="129467576300000000" />
<file name="icon-16-messages.png" server="C:/wamp/www/redampliado/" local="129467576280000000" remote="129467576280000000" />
<file name="icon-16-logout.png" server="C:/wamp/www/redampliado/" local="129467576300000000" remote="129467576300000000" />
<file name="icon-16-config.png" server="C:/wamp/www/redampliado/" local="129467576320000000" remote="129467576320000000" />
<file name="icon-16-red-catasocdepmd.png" server="C:/wamp/www/redampliado/" local="130150142042851188" remote="130150142040000000" />
<file name="icon-16-costo.png" server="C:/wamp/www/SITDBCS/" local="129650147000000000" remote="129650147000000000" />
<file name="icon-16-autoventa.png" server="C:/wamp/www/SITDBCS/" local="129482685260000000" remote="129482685260000000" />
<file name="icon-16-imprimirhistorial.png" server="C:/wamp/www/SITDBCS/" local="129482705660000000" remote="129482705660000000" />
<file name="icon-16-adeudo.png" server="C:/wamp/www/SITDBCS/" local="129482674320000000" remote="129482674320000000" />
<file name="icon-16-pagos.png" server="C:/wamp/www/SITDBCS/" local="129482639660000000" remote="129482639660000000" />
<file name="icon-16-vencimientos.png" server="C:/wamp/www/SITDBCS/" local="129482677340000000" remote="129482677340000000" />
<file name="icon-16-abono.png" server="C:/wamp/www/SITDBCS/" local="129482621700000000" remote="129482621700000000" />
<file name="icon-16-resumen.png" server="C:/wamp/www/SITDBCS/" local="129482554420000000" remote="129482554420000000" />
<file name="icon-16-deslinde.png" server="C:/wamp/www/SITDBCS/" local="129482555640000000" remote="129482555640000000" />
<file name="icon-16-pagares.png" server="C:/wamp/www/SITDBCS/" local="129482551380000000" remote="129482551380000000" />
<file name="icon-16-contrato.png" server="C:/wamp/www/SITDBCS/" local="129482549120000000" remote="129482549120000000" />
<file name="icon-16-cotizacion.png" server="C:/wamp/www/SITDBCS/" local="129481830660000000" remote="129481830660000000" />
<file name="icon-16-auto.png" server="C:/wamp/www/SITDBCS/" local="129481759540000000" remote="129481759540000000" />
<file name="icon-16-cliente.png" server="C:/wamp/www/SITDBCS/" local="129481770940000000" remote="129481770940000000" />
<file name="icon-16-clienteaval.png" server="C:/wamp/www/SITDBCS/" local="129594188960000000" remote="129594188960000000" />
<file name="icon-16-cpanel.png" server="C:/wamp/www/SITDBCS/" local="129467576320000000" remote="129467576320000000" />
<file name="icon-16-user.png" server="C:/wamp/www/SITDBCS/" local="129467576260000000" remote="129467576260000000" />
<file name="icon-16-red-rama.png" server="C:/wamp/www/SITDBCS/" local="129804521480000000" remote="129804521480000000" />
<file name="icon-16-red-modalidadentedep.png" server="C:/wamp/www/SITDBCS/" local="129804528800000000" remote="129804528800000000" />
<file name="icon-16-red-deportes.png" server="C:/wamp/www/SITDBCS/" local="129804530160000000" remote="129804530160000000" />
<file name="icon-16-red-club.png" server="C:/wamp/www/SITDBCS/" local="129804532400000000" remote="129804532400000000" />
<file name="icon-16-red-liga.png" server="C:/wamp/www/SITDBCS/" local="129804537060000000" remote="129804537060000000" />
<file name="icon-16-red-eventonacional.png" server="C:/wamp/www/SITDBCS/" local="129804538460000000" remote="129804538460000000" />
<file name="icon-16-red-municipio.png" server="C:/wamp/www/SITDBCS/" local="129804542440000000" remote="129804542440000000" />
<file name="icon-16-red-asociaciondep.png" server="C:/wamp/www/SITDBCS/" local="129804550520000000" remote="129804550520000000" />
<file name="icon-16-red-pruebas.png" server="C:/wamp/www/SITDBCS/" local="129804561520000000" remote="129804561520000000" />
<file name="icon-16-red-modalidaddeportiva.png" server="C:/wamp/www/SITDBCS/" local="129804607420000000" remote="129804607420000000" />
<file name="icon-16-red-eventointernacional.png" server="C:/wamp/www/SITDBCS/" local="129804609940000000" remote="129804609940000000" />
<file name="icon-16-red-estado.png" server="C:/wamp/www/SITDBCS/" local="129804612120000000" remote="129804612120000000" />
<file name="icon-16-red-categoria.png" server="C:/wamp/www/SITDBCS/" local="129804619340000000" remote="129804619340000000" />
<file name="icon-16-red-vincularasociaciondep.png" server="C:/wamp/www/SITDBCS/" local="129805382800000000" remote="129805382800000000" />
<file name="icon-16-red-imprimirasociaciondep.png" server="C:/wamp/www/SITDBCS/" local="129805412180000000" remote="129805412180000000" />
<file name="icon-16-red-imprimirsirred.png" server="C:/wamp/www/SITDBCS/" local="129805414760000000" remote="129805414760000000" />
<file name="icon-16-red-cedulainscripcion.png" server="C:/wamp/www/SITDBCS/" local="129805416680000000" remote="129805416680000000" />
<file name="icon-16-red-imprimircredencial.png" server="C:/wamp/www/SITDBCS/" local="129805422880000000" remote="129805422880000000" />
<file name="icon-16-red-reporteasociaciondep.png" server="C:/wamp/www/SITDBCS/" local="129805426500000000" remote="129805426500000000" />
<file name="icon-16-red-vincularevaluacionseg.png" server="C:/wamp/www/SITDBCS/" local="129805506840000000" remote="129805506840000000" />
<file name="icon-16-red-imprimirevaluacionseg.png" server="C:/wamp/www/SITDBCS/" local="129805511700000000" remote="129805511700000000" />
<file name="icon-16-red-curriculumevaluacionseg.png" server="C:/wamp/www/SITDBCS/" local="129805515340000000" remote="129805515340000000" />
<file name="icon-16-red-reporteevaluacionseg.png" server="C:/wamp/www/SITDBCS/" local="129806271520000000" remote="129806271520000000" />
<file name="icon-16-red-vinculareventodep.png" server="C:/wamp/www/SITDBCS/" local="129806358620000000" remote="129806358620000000" />
<file name="icon-16-red-validareventodep.png" server="C:/wamp/www/SITDBCS/" local="129806360500000000" remote="129806360500000000" />
<file name="icon-16-red-resultadoeventodep.png" server="C:/wamp/www/SITDBCS/" local="129806363440000000" remote="129806363440000000" />
<file name="icon-16-red-impimireventodep.png" server="C:/wamp/www/SITDBCS/" local="129806373100000000" remote="129806373100000000" />
<file name="icon-16-red-impimircedulaeventodep.png" server="C:/wamp/www/SITDBCS/" local="129806374940000000" remote="129806374940000000" />
<file name="icon-16-red-impimirgaffeteseventodep.png" server="C:/wamp/www/SITDBCS/" local="129808854640000000" remote="129808854640000000" />
<file name="icon-16-red-reporteeventodep.png" server="C:/wamp/www/SITDBCS/" local="129808868520000000" remote="129808868520000000" />
<file name="icon-16-red-imprimirreportecredencial.png" server="C:/wamp/www/SITDBCS/" local="129808871360000000" remote="129808871360000000" />
<file name="icon-16-red-reportes.png" server="C:/wamp/www/SITDBCS/" local="129808875980000000" remote="129808875980000000" />
<file name="icon-16-red-status.png" server="C:/wamp/www/SITDBCS/" local="129808877620000000" remote="129808877620000000" />
<file name="icon-16-red-catasocdepmd.png" server="C:/wamp/www/SITDBCS/" local="130150142060000000" remote="130150142060000000" />
<file name="icon-16-media.png" server="C:/wamp/www/SITDBCS/" local="129467576300000000" remote="129467576300000000" />
<file name="icon-16-messages.png" server="C:/wamp/www/SITDBCS/" local="129467576280000000" remote="129467576280000000" />
<file name="icon-16-logout.png" server="C:/wamp/www/SITDBCS/" local="129467576300000000" remote="129467576300000000" />
<file name="icon-16-config.png" server="C:/wamp/www/SITDBCS/" local="129467576320000000" remote="129467576320000000" />
</dwsync>